{
    "improvement_list": [
        {
            "end_line": 10,
            "improvement_desc": "Potential division by zero error in line 10. Add a check to ensure y is not zero before the division.",
            "start_line": 10,
            "type_of_improvement": "safety"
        },
        {
            "end_line": 5,
            "improvement_desc": "The variable 'x' is modified inside the loop, but its initial value is not used. It might be beneficial to check the effect of the initial value of x on the loop execution.",
            "start_line": 5,
            "type_of_improvement": "logic"
        },
        {
            "end_line": 7,
            "improvement_desc": "The condition 'x % 2' in line 7 always evaluates to 0 or 1. This makes the condition and control flow more understandable. However, the loop is designed so that y will alternate between 0 and 4. This may not be intended. Analyze the loop logic and update this conditional statement.",
            "start_line": 7,
            "type_of_improvement": "logic"
        }
    ]
}